tethys/__init__.py
tethys/cli.py
tethys/docs.py
tethys/foobar.py
tethys_template-1.0.3.dist-info/LICENSE
tethys_template-1.0.3.dist-info/METADATA
tethys_template-1.0.3.dist-info/WHEEL
tethys_template-1.0.3.dist-info/entry_points.txt
tethys_template-1.0.3.dist-info/top_level.txt
tethys_template-1.0.3.dist-info/RECORD
