Metadata-Version: 2.1
Name: tethys-template
Version: 1.0.3
Summary: A python package template with tox testing environments.
Author-email: Pat Sagan <pcsagan@gmail.com>
License: MIT License
Project-URL: Code, https://github.com/pcsagan/tethys
Project-URL: Issues, https://github.com/pcsagan/tethys/issues
Project-URL: Actions, https://github.com/pcsagan/tethys/actions
Keywords: tethys-template
Classifier: License :: OSI Approved :: MIT License
Classifier: Programming Language :: Python :: 3
Classifier: Development Status :: 5 - Production/Stable
Classifier: Framework :: Flake8
Classifier: Framework :: Pytest
Classifier: Framework :: tox
Classifier: Natural Language :: English
Classifier: Operating System :: MacOS :: MacOS X
Classifier: Operating System :: Microsoft :: Windows
Classifier: Operating System :: POSIX :: Linux
Classifier: Typing :: Typed
Requires-Python: >=3.9
License-File: LICENSE
Requires-Dist: requests
